Wikkid-0.5.data/data/share/man/man1/wikkid-serve.1
Wikkid-0.5.data/scripts/wikkid-serve
plugin/__init__.py
plugin/commands.py
wikkid/__init__.py
wikkid/app.py
wikkid/context.py
wikkid/dispatcher.py
wikkid/fileutils.py
wikkid/contrib/__init__.py
wikkid/filestore/__init__.py
wikkid/filestore/basefile.py
wikkid/filestore/bzr.py
wikkid/filestore/git.py
wikkid/filestore/volatile.py
wikkid/formatter/__init__.py
wikkid/formatter/markdownformatter.py
wikkid/formatter/pygmentsformatter.py
wikkid/formatter/registry.py
wikkid/formatter/restformatter.py
wikkid/formatter/textileformatter.py
wikkid/interface/__init__.py
wikkid/interface/filestore.py
wikkid/interface/formatter.py
wikkid/interface/resource.py
wikkid/interface/user.py
wikkid/model/__init__.py
wikkid/model/baseresource.py
wikkid/model/binary.py
wikkid/model/directory.py
wikkid/model/factory.py
wikkid/model/file.py
wikkid/model/missing.py
wikkid/model/root.py
wikkid/model/sourcetext.py
wikkid/model/textfile.py
wikkid/model/wikitext.py
wikkid/skin/__init__.py
wikkid/skin/loader.py
wikkid/skin/__pycache__/__init__.cpython-310.pyc
wikkid/skin/__pycache__/loader.cpython-310.pyc
wikkid/skin/default/base.html
wikkid/skin/default/directory_listing.html
wikkid/skin/default/edit.html
wikkid/skin/default/favicon.ico
wikkid/skin/default/missing-directory.html
wikkid/skin/default/missing-page.html
wikkid/skin/default/page.html
wikkid/skin/default/static/attach.gif
wikkid/skin/default/static/bg-header.gif
wikkid/skin/default/static/bg-navbar.gif
wikkid/skin/default/static/btn-login.gif
wikkid/skin/default/static/default.css
wikkid/skin/default/static/ico_file.gif
wikkid/skin/default/static/ico_folder.gif
wikkid/skin/default/static/ico_folder_up.gif
wikkid/skin/default/static/icon-blank.gif
wikkid/skin/default/static/icon-mailto.gif
wikkid/skin/default/static/logo.png
wikkid/skin/default/static/preview.png
wikkid/tests/__init__.py
wikkid/tests/factory.py
wikkid/tests/fakes.py
wikkid/tests/filestore.py
wikkid/tests/test_app.py
Wikkid-0.5.dist-info/LICENCE
Wikkid-0.5.dist-info/METADATA
Wikkid-0.5.dist-info/WHEEL
Wikkid-0.5.dist-info/top_level.txt
Wikkid-0.5.dist-info/RECORD
