Metadata-Version: 2.1
Name: Wikkid
Version: 0.5
Summary: VCS-backed wiki
Home-page: https://launchpad.net/wikkid
Author: Wikkid Developers
Author-email: wikkid-dev@lists.launchpad.net
Project-URL: Repository, https://github.com/wikkid-team/wikkid
License-File: LICENCE
Requires-Dist: breezy
Requires-Dist: docutils
Requires-Dist: dulwich
Requires-Dist: jinja2
Requires-Dist: merge3
Requires-Dist: pygments
Requires-Dist: twisted
Requires-Dist: webob
Requires-Dist: zope.interface
Provides-Extra: dev
Requires-Dist: bs4 ; extra == 'dev'
Requires-Dist: lxml ; extra == 'dev'
Requires-Dist: testtools ; extra == 'dev'
